{
  "api": {
    "owner_id": "ID OF THE OWNERS ACCOUNT HERE",
    "token": "IF YOUR ACCOUNT IS OF BOT TYPE - THIS NEEDS TO BE FILLED OUT WITH YOUR API TOKEN",
    "status": "DEFAULT STATUS OF BOT",
    "prefix": "DEFAULT PREFIX FOR COMMANDS",
    "is_bot_account": "TRUE IF ACCOUNT IS OF BOT TYPE, FALSE OTHERWISE"
  },
  "channels" : {

  },
  "functions": {
    "FUNCTION-TRIGGER": "ACTION"
  },
  "reddit": {
    "username": "REDDIT USERNAME HERE",
    "password": "REDDIT PASSWORD HERE",
    "client_id": "REDDIT CLIENT ID HERE",
    "client_secret": "REDDIT CLIENT SECRET"
  },
  "users": {
    "USER": "ID",
    "_COMMENT": "THIS USER ARRAY WILL BE FILLED ON CALL OF THE ID COMMAND"
  }

}